odoo/addons/vault/README.rst
odoo/addons/vault/TECHNICAL.rst
odoo/addons/vault/__init__.py
odoo/addons/vault/__manifest__.py
odoo/addons/vault/controllers/__init__.py
odoo/addons/vault/controllers/main.py
odoo/addons/vault/i18n/es.po
odoo/addons/vault/i18n/it.po
odoo/addons/vault/i18n/nl.po
odoo/addons/vault/i18n/vault.pot
odoo/addons/vault/models/__init__.py
odoo/addons/vault/models/abstract_vault.py
odoo/addons/vault/models/abstract_vault_field.py
odoo/addons/vault/models/res_config_settings.py
odoo/addons/vault/models/res_users.py
odoo/addons/vault/models/res_users_key.py
odoo/addons/vault/models/vault.py
odoo/addons/vault/models/vault_entry.py
odoo/addons/vault/models/vault_field.py
odoo/addons/vault/models/vault_file.py
odoo/addons/vault/models/vault_inbox.py
odoo/addons/vault/models/vault_inbox_log.py
odoo/addons/vault/models/vault_log.py
odoo/addons/vault/models/vault_right.py
odoo/addons/vault/models/vault_tag.py
odoo/addons/vault/readme/CONTRIBUTORS.md
odoo/addons/vault/readme/DESCRIPTION.md
odoo/addons/vault/readme/ROADMAP.md
odoo/addons/vault/security/ir.model.access.csv
odoo/addons/vault/security/ir_rule.xml
odoo/addons/vault/security/vault_security.xml
odoo/addons/vault/static/description/icon.png
odoo/addons/vault/static/description/index.html
odoo/addons/vault/static/lib/kdbxweb/kdbxweb.min.js
odoo/addons/vault/static/src/backend/controller.esm.js
odoo/addons/vault/static/src/backend/export.esm.js
odoo/addons/vault/static/src/backend/import.esm.js
odoo/addons/vault/static/src/backend/list_renderer.esm.js
odoo/addons/vault/static/src/backend/templates.xml
odoo/addons/vault/static/src/backend/user_menu.esm.js
odoo/addons/vault/static/src/backend/vault.esm.js
odoo/addons/vault/static/src/backend/vault.scss
odoo/addons/vault/static/src/backend/fields/templates.xml
odoo/addons/vault/static/src/backend/fields/vault_export_file.esm.js
odoo/addons/vault/static/src/backend/fields/vault_field.esm.js
odoo/addons/vault/static/src/backend/fields/vault_file.esm.js
odoo_addon_vault-18.0.1.0.1.dist-info/METADATA
odoo_addon_vault-18.0.1.0.1.dist-info/WHEEL
odoo_addon_vault-18.0.1.0.1.dist-info/top_level.txt
odoo_addon_vault-18.0.1.0.1.dist-info/RECORD
